<annotation>
	<folder>JPEGImage</folder>
	<filename>edge_bite77_crop.jpg</filename>
	<path>F:\paper\wafer\dataset\WaferData/voc_wafer_dataset\VOC\VOC2007(finlly)\VOC(Row)\edge_bite\Annotation/edge_bite77_crop.jpg</path>
	<source>
		<database>Unknown</database>
	</source>
	<size>
		<width>1280</width>
		<height>720</height>
		<depth>3</depth>
	</size>
	<segmented>0</segmented>
	<object>
		<name>open</name>
		<pose>Unspecified</pose>
		<truncated>0</truncated>
		<difficult>0</difficult>
		<bndbox>
			<xmin>376</xmin>
			<ymin>92</ymin>
			<xmax>408</xmax>
			<ymax>178</ymax>
		</bndbox>
	</object>
	<object>
		<name>edge_bite</name>
		<pose>Unspecified</pose>
		<truncated>1</truncated>
		<difficult>0</difficult>
		<bndbox>
			<xmin>164</xmin>
			<ymin>1</ymin>
			<xmax>195</xmax>
			<ymax>22</ymax>
		</bndbox>
	</object>
	<object>
		<name>stains_enbedded</name>
		<pose>Unspecified</pose>
		<truncated>0</truncated>
		<difficult>0</difficult>
		<bndbox>
			<xmin>1091</xmin>
			<ymin>547</ymin>
			<xmax>1119</xmax>
			<ymax>583</ymax>
		</bndbox>
	</object>
</annotation>