<annotation>
	<folder>JPEGImage</folder>
	<filename>open_98.jpg</filename>
	<path>F:\paper\wafer\dataset\WaferData\voc_wafer_dataset\VOC\open\JPEGImage\open_98.jpg</path>
	<source>
		<database>Unknown</database>
	</source>
	<size>
		<width>1280</width>
		<height>720</height>
		<depth>3</depth>
	</size>
	<segmented>0</segmented>
	<object>
		<name>open</name>
		<pose>Unspecified</pose>
		<truncated>0</truncated>
		<difficult>0</difficult>
		<bndbox>
			<xmin>471</xmin>
			<ymin>409</ymin>
			<xmax>510</xmax>
			<ymax>492</ymax>
		</bndbox>
	</object>
</annotation>
