<annotation>
	<folder>JPEGImage</folder>
	<filename>scratch_55.jpg</filename>
	<path>F:\paper\wafer\dataset\WaferData\voc_wafer_dataset\VOC\scratch\JPEGImage\scratch_55.jpg</path>
	<source>
		<database>Unknown</database>
	</source>
	<size>
		<width>1280</width>
		<height>720</height>
		<depth>3</depth>
	</size>
	<segmented>0</segmented>
	<object>
		<name>stains_enbedded</name>
		<pose>Unspecified</pose>
		<truncated>0</truncated>
		<difficult>0</difficult>
		<bndbox>
			<xmin>254</xmin>
			<ymin>548</ymin>
			<xmax>284</xmax>
			<ymax>578</ymax>
		</bndbox>
	</object>
	<object>
		<name>stains_enbedded</name>
		<pose>Unspecified</pose>
		<truncated>0</truncated>
		<difficult>0</difficult>
		<bndbox>
			<xmin>28</xmin>
			<ymin>357</ymin>
			<xmax>78</xmax>
			<ymax>384</ymax>
		</bndbox>
	</object>
	<object>
		<name>scratch</name>
		<pose>Unspecified</pose>
		<truncated>1</truncated>
		<difficult>0</difficult>
		<bndbox>
			<xmin>1213</xmin>
			<ymin>1</ymin>
			<xmax>1270</xmax>
			<ymax>100</ymax>
		</bndbox>
	</object>
</annotation>
